LICENSE
naif_eop_historical/__init__.py
naif_eop_historical/earth_620120_240827.bpc
naif_eop_historical/earth_620120_240827.md5
naif_eop_historical/fetch.py
naif_eop_historical/tests/__init__.py
naif_eop_historical/tests/test_naif_historical.py
naif_eop_historical-2024.8.28.1.dist-info/licenses/LICENSE
naif_eop_historical-2024.8.28.1.dist-info/METADATA
naif_eop_historical-2024.8.28.1.dist-info/WHEEL
naif_eop_historical-2024.8.28.1.dist-info/top_level.txt
naif_eop_historical-2024.8.28.1.dist-info/RECORD
