Metadata-Version: 2.4
Name: naif_eop_historical
Version: 2024.8.28.1
Summary: NAIF Historical Earth Orientation Parameters (EOP) Kernel for SPICE
Author-email: B612 Asteroid Institute <info@b612foundation.org>
License: MIT License
Requires-Python: >=3.7
License-File: LICENSE
Provides-Extra: tests
Requires-Dist: pytest; extra == "tests"
Requires-Dist: spiceypy; extra == "tests"
Dynamic: license-file
